fxr.py
fxr-0.2.5.dist-info/DESCRIPTION.rst
fxr-0.2.5.dist-info/METADATA
fxr-0.2.5.dist-info/RECORD
fxr-0.2.5.dist-info/WHEEL
fxr-0.2.5.dist-info/entry_points.txt
fxr-0.2.5.dist-info/metadata.json
fxr-0.2.5.dist-info/top_level.txt
