Metadata-Version: 2.0
Name: fxr
Version: 0.2.5
Summary: Pythonic Find and Replacetest
Home-page: https://github.com/pmav99/fxr
Author: Panos Mavrogiorgos
Author-email: pmav99@gmail.com
License: MIT license
Keywords: fxr,search,find,replace,find and replace,search and replace
Platform: UNKNOWN
Classifier: Development Status :: 4 - Beta
Classifier: Intended Audience :: Developers
Classifier: Environment :: Console
Classifier: License :: OSI Approved :: BSD License
Classifier: Natural Language :: English
Classifier: Topic :: Software Development
Classifier: Topic :: System
Classifier: Topic :: Utilities
Classifier: Programming Language :: Python :: 2.7
Classifier: Programming Language :: Python :: 3
Classifier: Programming Language :: Python :: 3.3
Classifier: Programming Language :: Python :: 3.4
Classifier: Programming Language :: Python :: 3.5
Classifier: Programming Language :: Python :: 3.6
